todo_indicator/indicator.py
todo_indicator/main.py
todo_indicator/img/panel-icon-dark.svg
todo_indicator/img/panel-icon-light.svg
todo_indicator/todotxt/__init__.py
todo_indicator/todotxt/item.py
todo_indicator/todotxt/list.py
todo_indicator/todotxt/test_item.py
todo_indicator/todotxt/test_list.py
todo_indicator-0.7.0.dist-info/METADATA
todo_indicator-0.7.0.dist-info/WHEEL
todo_indicator-0.7.0.dist-info/entry_points.txt
todo_indicator-0.7.0.dist-info/licenses/LICENSE
todo_indicator-0.7.0.dist-info/RECORD
