Metadata-Version: 2.3
Name: todo-indicator
Version: 0.7.0
Summary: An Ubuntu app indicator for todo.txt-style todo lists
Project-URL: GitHub, https://github.com/keithfancher/todo-indicator
Author: Keith Fancher
License-File: LICENSE
Keywords: appindicator,indicator,todo,todo.txt
Classifier: Development Status :: 5 - Production/Stable
Classifier: License :: OSI Approved :: GNU General Public License v3 (GPLv3)
Classifier: Operating System :: POSIX :: Linux
Classifier: Programming Language :: Python :: 3
Requires-Python: >=3
Requires-Dist: pyinotify
